sly_py_library/__init__.py
sly_py_library/upload/__init__.py
sly_py_library/upload/api/__init__.py
sly_py_library/upload/api/service.py
sly_py_library/upload/core/__init__.py
sly_py_library/upload/core/data_adapter/__init__.py
sly_py_library/upload/core/data_adapter/base.py
sly_py_library/upload/core/data_adapter/csv.py
sly_py_library/upload/core/upload_service/__init__.py
sly_py_library/upload/core/upload_service/base.py
sly_py_library/upload/core/upload_service/ftp.py
sly_py_library/upload/errors/__init__.py
sly_py_library/upload/errors/base.py
sly_py_library/upload/errors/upload_error.py
sly_py_library/upload/test/__init__.py
sly_py_library/upload/test/test_ftp.py
sly_py_library/upload/types/__init__.py
sly_py_library/upload/types/client.py
sly_py_library/upload/types/ftp.py
sly_py_library-0.1.0.dist-info/METADATA
sly_py_library-0.1.0.dist-info/WHEEL
sly_py_library-0.1.0.dist-info/RECORD
